{
  "global_vars": {},
  "functions": {
    "foo": {
      "params": [
        [
          "a",
          "Int",
          false
        ]
      ],
      "return_type": "Int",
      "line": 2,
      "order": 0
    },
    "fao": {
      "params": [
        [
          "a",
          "String",
          false
        ]
      ],
      "return_type": "Unit",
      "line": 8,
      "order": 1
    },
    "bao": {
      "params": [
        [
          "alpha",
          "Int",
          false
        ],
        [
          "betta",
          "Int",
          false
        ]
      ],
      "return_type": "Int",
      "line": 11,
      "order": 2
    },
    "main": {
      "params": [],
      "return_type": "Unit",
      "line": 13,
      "order": 3
    }
  },
  "function_vars": {
    "foo": {
      "a": {
        "type": "Int",
        "initialized": true,
        "mutable": false,
        "line": 2
      },
      "b": {
        "type": "Int",
        "initialized": true,
        "mutable": true,
        "line": 3
      },
      "c": {
        "type": "Int",
        "initialized": true,
        "mutable": false,
        "line": 4
      }
    },
    "fao": {
      "a": {
        "type": "String",
        "initialized": true,
        "mutable": false,
        "line": 8
      }
    },
    "bao": {
      "alpha": {
        "type": "Int",
        "initialized": true,
        "mutable": false,
        "line": 11
      },
      "betta": {
        "type": "Int",
        "initialized": true,
        "mutable": false,
        "line": 11
      }
    },
    "main": {
      "a": {
        "type": "Int",
        "initialized": true,
        "mutable": false,
        "line": 14
      },
      "b": {
        "type": "Int",
        "initialized": true,
        "mutable": true,
        "line": 15
      }
    }
  }
}